demo_pipewire_filtertools/__init__.py
demo_pipewire_filtertools/main.py
demo_pipewire_filtertools-0.2.0.dist-info/licenses/LICENSE
demo_pipewire_filtertools-0.2.0.dist-info/METADATA
demo_pipewire_filtertools-0.2.0.dist-info/WHEEL
demo_pipewire_filtertools-0.2.0.dist-info/entry_points.txt
demo_pipewire_filtertools-0.2.0.dist-info/top_level.txt
demo_pipewire_filtertools-0.2.0.dist-info/RECORD
