Metadata-Version: 2.4
Name: demo-pipewire-filtertools
Version: 0.2.0
Summary: Demo app for PipeWire filter tools C library and Python bindings
Author-email: develOseven <devel.oseven@gmail.com>
License-Expression: MIT
Project-URL: Homepage, https://github.com/develOseven/demo-pipewire-filtertools
Project-URL: Issues, https://github.com/develOseven/demo-pipewire-filtertools/issues
Classifier: Programming Language :: Python :: 3
Classifier: Operating System :: POSIX :: Linux
License-File: LICENSE
Requires-Dist: pipewire-filtertools
Dynamic: license-file
